pipedream_utils/__init__.py
pipedream_utils/formatting/__init__.py
pipedream_utils/formatting/ascii.py
pipedream_utils/publishing/__init__.py
pipedream_utils/publishing/telegram.py
pipedream_utils-0.0.11.dist-info/METADATA
pipedream_utils-0.0.11.dist-info/WHEEL
pipedream_utils-0.0.11.dist-info/top_level.txt
pipedream_utils-0.0.11.dist-info/RECORD
